{
    "key": "group_54d22644ed0ee",
    "title": "Slider",
    "fields": [
        {
            "key": "field_54d383e7776a4",
            "label": "Slide",
            "name": "bene_add_slide",
            "type": "repeater",
            "instructions": "",
            "required": 0,
            "conditional_logic": 0,
            "wrapper": {
                "width": "",
                "class": "",
                "id": ""
            },
            "min": "",
            "max": "",
            "layout": "block",
            "button_label": "Add Slide",
            "sub_fields": [
                {
                    "key": "field_54d38400776a5",
                    "label": "Slide Type",
                    "name": "bene_slide_type",
                    "type": "select",
                    "instructions": "",
                    "required": 0,
                    "conditional_logic": 0,
                    "wrapper": {
                        "width": "",
                        "class": "one-half",
                        "id": ""
                    },
                    "choices": {
                        "choose": "Choose",
                        "image": "Image Only",
                        "text": "Text"
                    },
                    "default_value": {
                        "choose": "choose"
                    },
                    "allow_null": 0,
                    "multiple": 0,
                    "ui": 0,
                    "ajax": 0,
                    "placeholder": "",
                    "disabled": 0,
                    "readonly": 0,
                    "return_format": "value"
                },
                {
                    "key": "field_54d3842b776a6",
                    "label": "Image",
                    "name": "bene_slider_image",
                    "type": "image",
                    "instructions": "",
                    "required": 0,
                    "conditional_logic": [
                        [
                            {
                                "field": "field_54d38400776a5",
                                "operator": "==",
                                "value": "image"
                            }
                        ],
                        [
                            {
                                "field": "field_54d38400776a5",
                                "operator": "==",
                                "value": "text"
                            }
                        ]
                    ],
                    "wrapper": {
                        "width": "",
                        "class": "",
                        "id": ""
                    },
                    "return_format": "array",
                    "preview_size": "thumbnail",
                    "library": "all",
                    "min_width": 0,
                    "min_height": 0,
                    "min_size": 0,
                    "max_width": 0,
                    "max_height": 0,
                    "max_size": 0,
                    "mime_types": ""
                },
                {
                    "key": "field_54d38463776a8",
                    "label": "Text Type",
                    "name": "bene_slide_text_type",
                    "type": "select",
                    "instructions": "",
                    "required": 0,
                    "conditional_logic": [
                        [
                            {
                                "field": "field_54d38400776a5",
                                "operator": "==",
                                "value": "text"
                            }
                        ]
                    ],
                    "wrapper": {
                        "width": "",
                        "class": "one-half",
                        "id": ""
                    },
                    "choices": {
                        "plain-text": "Plain Text",
                        "callout": "Callout",
                        "quote": "Quote"
                    },
                    "default_value": {
                        "plain-text": "plain-text"
                    },
                    "allow_null": 0,
                    "multiple": 0,
                    "ui": 0,
                    "ajax": 0,
                    "placeholder": "",
                    "disabled": 0,
                    "readonly": 0,
                    "return_format": "value"
                },
                {
                    "key": "field_54d38599776ad",
                    "label": "Title",
                    "name": "bene_slide_title",
                    "type": "text",
                    "instructions": "",
                    "required": 0,
                    "conditional_logic": [
                        [
                            {
                                "field": "field_54d38400776a5",
                                "operator": "==",
                                "value": "text"
                            }
                        ]
                    ],
                    "wrapper": {
                        "width": 50,
                        "class": "one-half",
                        "id": ""
                    },
                    "default_value": "",
                    "placeholder": "",
                    "prepend": "",
                    "append": "",
                    "maxlength": "",
                    "readonly": 0,
                    "disabled": 0
                },
                {
                    "key": "field_54d384ca776aa",
                    "label": "Subtitle",
                    "name": "bene_slide_subtitle",
                    "type": "text",
                    "instructions": "",
                    "required": 0,
                    "conditional_logic": [
                        [
                            {
                                "field": "field_54d38400776a5",
                                "operator": "==",
                                "value": "text"
                            }
                        ]
                    ],
                    "wrapper": {
                        "width": 50,
                        "class": "one-half",
                        "id": ""
                    },
                    "default_value": "",
                    "placeholder": "",
                    "prepend": "",
                    "append": "",
                    "maxlength": "",
                    "readonly": 0,
                    "disabled": 0
                },
                {
                    "key": "field_54d38564776ab",
                    "label": "Text",
                    "name": "bene_slide_text",
                    "type": "wysiwyg",
                    "instructions": "",
                    "required": 0,
                    "conditional_logic": [
                        [
                            {
                                "field": "field_54d38400776a5",
                                "operator": "==",
                                "value": "text"
                            }
                        ]
                    ],
                    "wrapper": {
                        "width": "",
                        "class": "",
                        "id": ""
                    },
                    "default_value": "",
                    "tabs": "all",
                    "toolbar": "full",
                    "media_upload": 1
                },
                {
                    "key": "field_54d3857f776ac",
                    "label": "Button Text",
                    "name": "bene_slide_button_text",
                    "type": "text",
                    "instructions": "",
                    "required": 0,
                    "conditional_logic": [
                        [
                            {
                                "field": "field_54d38400776a5",
                                "operator": "==",
                                "value": "text"
                            }
                        ]
                    ],
                    "wrapper": {
                        "width": 50,
                        "class": "one-half",
                        "id": ""
                    },
                    "default_value": "",
                    "placeholder": "",
                    "prepend": "",
                    "append": "",
                    "maxlength": "",
                    "readonly": 0,
                    "disabled": 0
                },
                {
                    "key": "field_54d385ee776ae",
                    "label": "Bottom Text",
                    "name": "bene_slide_bottom_text",
                    "type": "text",
                    "instructions": "",
                    "required": 0,
                    "conditional_logic": [
                        [
                            {
                                "field": "field_54d38400776a5",
                                "operator": "==",
                                "value": "text"
                            }
                        ]
                    ],
                    "wrapper": {
                        "width": 50,
                        "class": "one-half",
                        "id": ""
                    },
                    "default_value": "",
                    "placeholder": "",
                    "prepend": "",
                    "append": "",
                    "maxlength": "",
                    "readonly": 0,
                    "disabled": 0
                },
                {
                    "key": "field_54d38610776af",
                    "label": "URL Type",
                    "name": "bebe_slide_url_type",
                    "type": "radio",
                    "instructions": "",
                    "required": 0,
                    "conditional_logic": [
                        [
                            {
                                "field": "field_54d38400776a5",
                                "operator": "==",
                                "value": "image"
                            }
                        ],
                        [
                            {
                                "field": "field_54d38400776a5",
                                "operator": "==",
                                "value": "text"
                            }
                        ]
                    ],
                    "wrapper": {
                        "width": "",
                        "class": "",
                        "id": ""
                    },
                    "choices": {
                        "none": "None",
                        "url": "URL",
                        "page": "Page"
                    },
                    "other_choice": 0,
                    "save_other_choice": 0,
                    "default_value": "",
                    "layout": "horizontal",
                    "allow_null": 0,
                    "return_format": "value"
                },
                {
                    "key": "field_54d38653776b1",
                    "label": "URL",
                    "name": "bene_slide_url",
                    "type": "url",
                    "instructions": "",
                    "required": 0,
                    "conditional_logic": [
                        [
                            {
                                "field": "field_54d38610776af",
                                "operator": "==",
                                "value": "url"
                            }
                        ]
                    ],
                    "wrapper": {
                        "width": "",
                        "class": "",
                        "id": ""
                    },
                    "default_value": "",
                    "placeholder": ""
                },
                {
                    "key": "field_54d387a9e037c",
                    "label": "Page",
                    "name": "bene_slide_page",
                    "type": "page_link",
                    "instructions": "",
                    "required": 0,
                    "conditional_logic": [
                        [
                            {
                                "field": "field_54d38610776af",
                                "operator": "==",
                                "value": "page"
                            }
                        ]
                    ],
                    "wrapper": {
                        "width": "",
                        "class": "",
                        "id": ""
                    },
                    "post_type": [],
                    "taxonomy": [],
                    "allow_null": 0,
                    "multiple": 0,
                    "allow_archives": 1
                }
            ],
            "collapsed": ""
        }
    ],
    "location": [
        [
            {
                "param": "post_type",
                "operator": "==",
                "value": "slider"
            }
        ]
    ],
    "menu_order": 0,
    "position": "normal",
    "style": "seamless",
    "label_placement": "top",
    "instruction_placement": "label",
    "hide_on_screen": [
        "permalink",
        "the_content",
        "excerpt",
        "custom_fields",
        "discussion",
        "comments",
        "revisions",
        "slug",
        "author",
        "format",
        "page_attributes",
        "featured_image",
        "categories",
        "tags",
        "send-trackbacks"
    ],
    "active": 1,
    "description": "",
    "modified": 1480480484
}